rjj/__init__.py
rjj/icon.png
rjj-1.0.5.dist-info/entry_points.txt
rjj-1.0.5.dist-info/LICENSE
rjj-1.0.5.dist-info/WHEEL
rjj-1.0.5.dist-info/METADATA
rjj-1.0.5.dist-info/RECORD
