Metadata-Version: 2.1
Name: rjj
Version: 1.0.5
Summary: rjj (read-joint-jet) is a simple cmd-based data analysis/transforming wizard
Author-email: calcuis <info@calcu.io>
Classifier: License :: OSI Approved :: MIT License
Requires-Dist: pandas
Requires-Dist: numpy
Requires-Dist: scipy
Requires-Dist: statsmodels
Requires-Dist: scikit-learn
Requires-Dist: matplotlib
Requires-Dist: pillow
Requires-Dist: graphviz
Requires-Dist: fpdf2
Requires-Dist: pyminify
Project-URL: GitHub, https://github.com/calcuis/rjj
Project-URL: Homepage, https://7look.org
Project-URL: Issues, https://github.com/calcuis/rjj/issues
Project-URL: PyPI, https://pypi.org/project/rjj
